finter_laboratory/__init__.py
finter_laboratory/notebook.py
finter_laboratory-0.0.4.dist-info/DESCRIPTION.rst
finter_laboratory-0.0.4.dist-info/METADATA
finter_laboratory-0.0.4.dist-info/RECORD
finter_laboratory-0.0.4.dist-info/WHEEL
finter_laboratory-0.0.4.dist-info/metadata.json
finter_laboratory-0.0.4.dist-info/top_level.txt
