Metadata-Version: 2.0
Name: finter-laboratory
Version: 0.0.4
Summary: UNKNOWN
Home-page: UNKNOWN
License: UNKNOWN
Platform: UNKNOWN
Requires-Dist: requests
Requires-Dist: nbformat
